humcal/__init__.py
humcal/cli.py
humcal/humcal.py
humcal-1.1.2.dist-info/AUTHORS.rst
humcal-1.1.2.dist-info/LICENSE
humcal-1.1.2.dist-info/METADATA
humcal-1.1.2.dist-info/WHEEL
humcal-1.1.2.dist-info/top_level.txt
humcal-1.1.2.dist-info/RECORD
