Metadata-Version: 2.1
Name: humcal
Version: 1.1.2
Summary: Humidity calculations for industrial and meteorological calculations rotating around vapor pressure
Author-email: Julius Oskar Schaaf <julius.schaaf@gmail.com>
Maintainer-email: Julius Oskar Schaaf <julius.schaaf@gmail.com>
License: MIT license
Project-URL: bugs, https://github.com/OScurry/humcal/issues
Project-URL: changelog, https://github.com/OScurry/humcal/blob/master/changelog.md
Project-URL: homepage, https://github.com/OScurry/humcal
License-File: LICENSE
License-File: AUTHORS.rst
Requires-Dist: typer
Provides-Extra: dev
Requires-Dist: coverage; extra == "dev"
Requires-Dist: mypy; extra == "dev"
Requires-Dist: pytest; extra == "dev"
Requires-Dist: ruff; extra == "dev"
